{"openapi":"3.1.0","info":{"title":"FastAPI","version":"0.1.0"},"paths":{"/search/art":{"get":{"summary":"Search Art Route","operationId":"search_art_route_search_art_get","parameters":[{"name":"q","in":"query","required":true,"schema":{"type":"string","title":"Q"}}],"responses":{"200":{"description":"Successful Response","content":{"application/json":{"schema":{"type":"array","items":{"type":"string"},"title":"Response Search Art Route Search Art Get"}}}},"422":{"description":"Validation Error","content":{"application/json":{"schema":{"$ref":"#/components/schemas/HTTPValidationError"}}}}}}},"/search/user":{"get":{"summary":"Search User Route","operationId":"search_user_route_search_user_get","parameters":[{"name":"q","in":"query","required":true,"schema":{"type":"string","title":"Q"}}],"responses":{"200":{"description":"Successful Response","content":{"application/json":{"schema":{"type":"array","items":{"type":"string"},"title":"Response Search User Route Search User Get"}}}},"422":{"description":"Validation Error","content":{"application/json":{"schema":{"$ref":"#/components/schemas/HTTPValidationError"}}}}}}},"/recommend/art":{"get":{"summary":"Recommend Art Route","operationId":"recommend_art_route_recommend_art_get","parameters":[{"name":"art_id","in":"query","required":true,"schema":{"type":"string","title":"Art Id"}},{"name":"limit","in":"query","required":false,"schema":{"type":"integer","default":50,"title":"Limit"}}],"responses":{"200":{"description":"Successful Response","content":{"application/json":{"schema":{}}}},"422":{"description":"Validation Error","content":{"application/json":{"schema":{"$ref":"#/components/schemas/HTTPValidationError"}}}}}}},"/":{"get":{"summary":"Test","operationId":"test__get","responses":{"200":{"description":"Successful Response","content":{"application/json":{"schema":{}}}}}}}},"components":{"schemas":{"HTTPValidationError":{"properties":{"detail":{"items":{"$ref":"#/components/schemas/ValidationError"},"type":"array","title":"Detail"}},"type":"object","title":"HTTPValidationError"},"ValidationError":{"properties":{"loc":{"items":{"anyOf":[{"type":"string"},{"type":"integer"}]},"type":"array","title":"Location"},"msg":{"type":"string","title":"Message"},"type":{"type":"string","title":"Error Type"}},"type":"object","required":["loc","msg","type"],"title":"ValidationError"}}}}